ngeo/__init__.py
ngeo/_version.py
ngeo/core.py
ngeo/data.py
ngeo/geodesic.py
ngeo/geomarray.py
ngeo/io.py
ngeo/ops.py
ngeo/planar.py
ngeo/raster.py
ngeo/sparse_ops.py
ngeo/tests/__init__.py
ngeo/tests/test_core.py
ngeo/tests/test_data.py
ngeo/tests/test_ops.py
ngeo-0.0.1.dist-info/METADATA
ngeo-0.0.1.dist-info/WHEEL
ngeo-0.0.1.dist-info/top_level.txt
ngeo-0.0.1.dist-info/RECORD
