Metadata-Version: 2.1
Name: ngeo
Version: 0.0.1
Summary: Fast and accurate spatial analysis
Home-page: http://github.com/parietal-io/ngeo
Author: UNKNOWN
Author-email: UNKNOWN
License: UNKNOWN
Platform: UNKNOWN
